pytrackerfr/__init__.py
pytrackerfr/main.py
pytrackerfr/url_generator/__init__.py
pytrackerfr/url_generator/affiliation.py
pytrackerfr/url_generator/bing_ads.py
pytrackerfr/url_generator/colaboration.py
pytrackerfr/url_generator/comparateur.py
pytrackerfr/url_generator/core.py
pytrackerfr/url_generator/display.py
pytrackerfr/url_generator/emailing.py
pytrackerfr/url_generator/google_ads.py
pytrackerfr/url_generator/social.py
pytrackerfr-0.0.0.dist-info/METADATA
pytrackerfr-0.0.0.dist-info/WHEEL
pytrackerfr-0.0.0.dist-info/entry_points.txt
pytrackerfr-0.0.0.dist-info/top_level.txt
pytrackerfr-0.0.0.dist-info/RECORD
