Metadata-Version: 2.1
Name: pytrackerfr
Version: 0.0.0
Summary: Outil de génération d'URLs de tracking Eulerian.
Author: abutrag
Author-email: a.butragueno@eulerian.com
Classifier: Programming Language :: Python :: 3
Classifier: License :: OSI Approved :: MIT License
Classifier: Operating System :: OS Independent
Requires-Python: >=3.7
